FastXlsToCsv/XlConverter.py
FastXlsToCsv/_XlsToCsvExceptions.py
FastXlsToCsv/__init__.py
FastXlsToCsv-1.2.1.dist-info/LICENSE
FastXlsToCsv-1.2.1.dist-info/METADATA
FastXlsToCsv-1.2.1.dist-info/WHEEL
FastXlsToCsv-1.2.1.dist-info/top_level.txt
FastXlsToCsv-1.2.1.dist-info/RECORD
