Metadata-Version: 2.1
Name: FastXlsToCsv
Version: 1.2.1
Summary: A fast way to convert .xls and .xlsx to csv with vbs
Home-page: https://github.com/willayy/FastXlsToCsv
Author: William Norland
Author-email: williamnorland@gmail.com
License: MIT
Classifier: Operating System :: Microsoft :: Windows
Classifier: Operating System :: Microsoft :: Windows :: Windows 10
Classifier: Operating System :: Microsoft :: Windows :: Windows 11
Classifier: License :: OSI Approved :: MIT License
Classifier: Programming Language :: Python
Classifier: Programming Language :: Python :: 3
Classifier: Programming Language :: Python :: 3.11
License-File: LICENSE
